RP2040Home/RP2040Home.py
RP2040Home/__init__.py
RP2040Home/configparsing/__init__.py
RP2040Home/configparsing/configparser.py
RP2040Home/configparsing/homeassistantdiscoveryconfig.py
RP2040Home/configparsing/inputsanitisation.py
RP2040Home/configparsing/mqttconfig.py
RP2040Home/configparsing/output.py
RP2040Home/configparsing/wificonfig.py
RP2040Home/homeassistant/__init__.py
RP2040Home/homeassistant/discoveryPayload.py
RP2040Home/homeassistant/disoveryDevice.py
RP2040Home/homeassistant/mqttClient.py
RP2040Home/homeassistant/payloadGenerator.py
RP2040Home/test/__init__.py
RP2040Home/test/configparsing/__init__.py
RP2040Home/test/configparsing/configparsing_test.py
RP2040Home/test/configparsing/inputsanitisation_test.py
RP2040Home/test/configparsing/mqttconfig_test.py
RP2040Home/test/configparsing/output_test.py
RP2040Home-0.1.9.dist-info/LICENSE
RP2040Home-0.1.9.dist-info/METADATA
RP2040Home-0.1.9.dist-info/WHEEL
RP2040Home-0.1.9.dist-info/top_level.txt
RP2040Home-0.1.9.dist-info/RECORD
