Metadata-Version: 2.1
Name: RP2040Home
Version: 0.1.9
Summary: MQTT Client for RP2040 based boards which integrates into Home Assistant
Author: Ellington S
Author-email: 
Classifier: Programming Language :: Python :: 3
Classifier: License :: OSI Approved :: MIT License
Classifier: Operating System :: OS Independent
Requires-Python: >=3.6
License-File: LICENSE
